PyModMC/__init__.py
PyModMC/main.py
PyModMC-0.2.2a0.dist-info/METADATA
PyModMC-0.2.2a0.dist-info/WHEEL
PyModMC-0.2.2a0.dist-info/top_level.txt
PyModMC-0.2.2a0.dist-info/RECORD
