Metadata-Version: 2.1
Name: PyModMC
Version: 0.2.2a0
Summary: A Minecraft modding library made for Python.
Home-page: https://github.com/Fluxyn/PyModMC
Author: Fluxyn
Author-email: UNKNOWN
License: MIT
Platform: UNKNOWN
Classifier: Programming Language :: Python :: 3
Classifier: License :: OSI Approved :: MIT License
